{
  "languageTag": "en-US",
  "fileDescription": "Strings for flexbox_controller.",
  "text": {
    "plugins": {
      "flexbox_controller": {
        "name": "UI Controller",
        "description": "A plugin to control flexbox layouts in Construct 3 projects.",
        "help-url": "https://constructfund.github.io/construct3-ui",
        "aceCategories": {
          "general": "general"
        },
        "properties": {},
        "actions": {
          "RemoveClassProperty": {
            "list-name": "Remove Class Property",
            "display-text": "Remove property [b]{1}[/b] from class [b]{0}[/b]",
            "description": "Removes a property from a class",
            "params": {
              "className": {
                "name": "Class Name",
                "desc": "The name of the class to remove the property from"
              },
              "property": {
                "name": "Property",
                "desc": "The CSS property to remove"
              }
            }
          },
          "SetClassProperty": {
            "list-name": "Set Class Property",
            "display-text": "Set property [b]{1}[/b] to [b]{2}[/b] in class [b]{0}[/b]",
            "description": "Sets a property for a class",
            "params": {
              "className": {
                "name": "Class Name",
                "desc": "The name of the class to set the property for"
              },
              "property": {
                "name": "Property",
                "desc": "The CSS property to set"
              },
              "value": {
                "name": "Value",
                "desc": "The value to set for the property"
              }
            }
          },
          "SetClassStyle": {
            "list-name": "Declare Class",
            "display-text": "Declare class [b]{0}[/b] to [i]{1}[/i]",
            "description": "Sets the style for a class",
            "params": {
              "className": {
                "name": "Class Name",
                "desc": "The name of the class to set the style for"
              },
              "styleString": {
                "name": "Style String",
                "desc": "The CSS style string to apply to the class"
              }
            }
          }
        },
        "conditions": {},
        "expressions": {}
      }
    }
  }
}